{
  "maxOptions" : 4,
  "keyRows" : [ {
    "keys" : [ {
      "id" : 0,
      "type" : "FILLER",
      "size" : 0.3
    }, {
      "id" : 0,
      "type" : "FUNCTION",
      "size" : 2,
      "text" : "F1",
      "codeOptions" : [ "133", "133", "133", null ]
    }, {
      "id" : 0,
      "type" : "FUNCTION",
      "size" : 2,
      "text" : "F2",
      "codeOptions" : [ "137", "137", "137", null ]
    }, {
      "id" : 0,
      "type" : "FUNCTION",
      "size" : 2,
      "text" : "F3",
      "codeOptions" : [ "134", "134", "134", null ]
    }, {
      "id" : 0,
      "type" : "FUNCTION",
      "size" : 2,
      "text" : "F4",
      "codeOptions" : [ "138", "138", "138", null ]
    }, {
      "id" : 0,
      "type" : "FUNCTION",
      "size" : 2,
      "text" : "F5",
      "codeOptions" : [ "135", "135", "135", null ]
    }, {
      "id" : 0,
      "type" : "FUNCTION",
      "size" : 2,
      "text" : "F6",
      "codeOptions" : [ "139", "139", "139", null ]
    }, {
      "id" : 0,
      "type" : "FUNCTION",
      "size" : 2,
      "text" : "F7",
      "codeOptions" : [ "136", "136", "136", null ]
    }, {
      "id" : 0,
      "type" : "FUNCTION",
      "size" : 2,
      "text" : "F8",
      "codeOptions" : [ "140", "140", "140", null ]
    }, {
      "id" : 0,
      "type" : "OPTION",
      "name" : "REVERSE",
      "symbol" : true,
      "toggleButton" : true,
      "size" : 2,
      "index" : 8,
      "text" : "",
      "codeOptions" : [ "146", "18", null, null ]
    }, {
      "id" : 0,
      "type" : "OPTION",
      "name" : "UPPER_LOWER",
      "symbol" : true,
      "toggleButton" : true,
      "size" : 2,
      "index" : 4,
      "text" : "",
      "codeOptions" : [ "142", "14", null, null ]
    }, {
      "id" : 0,
      "type" : "FILLER",
      "size" : 0.3
    }, {
      "id" : 0,
      "type" : "FUNCTION",
      "name" : "RUN",
      "size" : 3,
      "text" : "RUN"
    } ]
  }, {
    "keys" : [ {
      "id" : 0,
      "type" : "FILLER",
      "size" : 0.3
    }, {
      "id" : 0,
      "type" : "COLOR",
      "size" : 1,
      "index" : 0,
      "text" : "BLACK",
      "codeOptions" : [ "144", "144", "144", null ]
    }, {
      "id" : 0,
      "type" : "COLOR",
      "size" : 1,
      "index" : 1,
      "text" : "WHITE",
      "codeOptions" : [ "5", "5", "5", null ]
    }, {
      "id" : 0,
      "type" : "COLOR",
      "size" : 1,
      "index" : 2,
      "text" : "RED",
      "codeOptions" : [ "28", "28", "28", null ]
    }, {
      "id" : 0,
      "type" : "COLOR",
      "size" : 1,
      "index" : 3,
      "text" : "CYAN",
      "codeOptions" : [ "159", "159", "159", null ]
    }, {
      "id" : 0,
      "type" : "COLOR",
      "size" : 1,
      "index" : 4,
      "text" : "PURPLE",
      "codeOptions" : [ "156", "156", "156", null ]
    }, {
      "id" : 0,
      "type" : "COLOR",
      "size" : 1,
      "index" : 5,
      "text" : "GREEN",
      "codeOptions" : [ "30", "30", "30", null ]
    }, {
      "id" : 0,
      "type" : "COLOR",
      "size" : 1,
      "index" : 6,
      "text" : "BLUE",
      "codeOptions" : [ "31", "31", "31", null ]
    }, {
      "id" : 0,
      "type" : "COLOR",
      "size" : 1,
      "index" : 7,
      "text" : "YELLOW",
      "codeOptions" : [ "158", "158", "158", null ]
    }, {
      "id" : 0,
      "type" : "COLOR",
      "size" : 1,
      "index" : 8,
      "text" : "ORANGE",
      "codeOptions" : [ "129", "129", "129", null ]
    }, {
      "id" : 0,
      "type" : "COLOR",
      "size" : 1,
      "index" : 9,
      "text" : "BROWN",
      "codeOptions" : [ "149", "149", "149", null ]
    }, {
      "id" : 0,
      "type" : "COLOR",
      "size" : 1,
      "index" : 10,
      "text" : "LIGHT RED",
      "codeOptions" : [ "150", "150", "150", null ]
    }, {
      "id" : 0,
      "type" : "COLOR",
      "size" : 1,
      "index" : 11,
      "text" : "DARK GRAY",
      "codeOptions" : [ "151", "151", "151", null ]
    }, {
      "id" : 0,
      "type" : "COLOR",
      "size" : 1,
      "index" : 12,
      "text" : "GRAY",
      "codeOptions" : [ "152", "152", "152", null ]
    }, {
      "id" : 0,
      "type" : "COLOR",
      "size" : 1,
      "index" : 13,
      "text" : "LIGHT GREEN",
      "codeOptions" : [ "153", "153", "153", null ]
    }, {
      "id" : 0,
      "type" : "COLOR",
      "size" : 1,
      "index" : 14,
      "text" : "LIGHT BLUE",
      "codeOptions" : [ "154", "154", "154", null ]
    }, {
      "id" : 0,
      "type" : "COLOR",
      "size" : 1,
      "index" : 15,
      "text" : "LIGHT GRAY",
      "codeOptions" : [ "155", "155", "155", null ]
    }, {
      "id" : 0,
      "type" : "FUNCTION",
      "symbol" : true,
      "name" : "CLEAR",
      "size" : 2,
      "text" : "",
      "codeOptions" : [ "147", "147", "147", null ]
    }, {
      "id" : 0,
      "type" : "FUNCTION",
      "symbol" : true,
      "name" : "HOME",
      "size" : 2,
      "text" : "",
      "codeOptions" : [ "19", "19", "19", null ]
    }, {
      "id" : 0,
      "type" : "FILLER",
      "size" : 0.3
    }, {
      "id" : 0,
      "type" : "FUNCTION",
      "name" : "LIST",
      "size" : 3,
      "text" : "LIST"
    } ]
  }, {
    "keys" : [ {
      "id" : 0,
      "type" : "FILLER",
      "size" : 0.3
    }, {
      "id" : 0,
      "type" : "KEY",
      "size" : 1,
      "text" : "",
      "codeOptions" : [ "95", "95", "95", null ],
      "displayOptions" : [ [ "", "", "", "" ], [ "", "", "", "" ], [ "", "", "", "" ] ]
    }, {
      "id" : 0,
      "type" : "KEY",
      "size" : 1,
      "text" : "1",
      "codeOptions" : [ "49", "33", "33", null ],
      "displayOptions" : [ [ "", "", "", "" ], [ "", "", "", "" ], [ "", "", "", "" ] ]
    }, {
      "id" : 0,
      "type" : "KEY",
      "size" : 1,
      "text" : "2",
      "codeOptions" : [ "50", "34", "34", null ],
      "displayOptions" : [ [ "", "", "", "" ], [ "", "", "", "" ], [ "", "", "", "" ] ]
    }, {
      "id" : 0,
      "type" : "KEY",
      "size" : 1,
      "text" : "3",
      "codeOptions" : [ "51", "35", "35", null ],
      "displayOptions" : [ [ "", "", "", "" ], [ "", "", "", "" ], [ "", "", "", "" ] ]
    }, {
      "id" : 0,
      "type" : "KEY",
      "size" : 1,
      "text" : "4",
      "codeOptions" : [ "52", "36", "36", null ],
      "displayOptions" : [ [ "", "", "", "" ], [ "", "", "", "" ], [ "", "", "", "" ] ]
    }, {
      "id" : 0,
      "type" : "KEY",
      "size" : 1,
      "text" : "5",
      "codeOptions" : [ "53", "37", "37", null ],
      "displayOptions" : [ [ "", "", "", "" ], [ "", "", "", "" ], [ "", "", "", "" ] ]
    }, {
      "id" : 0,
      "type" : "KEY",
      "size" : 1,
      "text" : "6",
      "codeOptions" : [ "54", "38", "38", null ],
      "displayOptions" : [ [ "", "", "", "" ], [ "", "", "", "" ], [ "", "", "", "" ] ]
    }, {
      "id" : 0,
      "type" : "KEY",
      "size" : 1,
      "text" : "7",
      "codeOptions" : [ "55", "39", "39", null ],
      "displayOptions" : [ [ "", "", "", "" ], [ "", "", "", "" ], [ "", "", "", "" ] ]
    }, {
      "id" : 0,
      "type" : "KEY",
      "size" : 1,
      "text" : "8",
      "codeOptions" : [ "56", "40", "40", null ],
      "displayOptions" : [ [ "", "", "", "" ], [ "", "", "", "" ], [ "", "", "", "" ] ]
    }, {
      "id" : 0,
      "type" : "KEY",
      "size" : 1,
      "text" : "9",
      "codeOptions" : [ "57", "41", "41", null ],
      "displayOptions" : [ [ "", "", "", "" ], [ "", "", "", "" ], [ "", "", "", "" ] ]
    }, {
      "id" : 0,
      "type" : "KEY",
      "size" : 1,
      "text" : "0",
      "codeOptions" : [ "48", "48", "48", null ],
      "displayOptions" : [ [ "", "", "", "" ], [ "", "", "", "" ], [ "", "", "", "" ] ]
    }, {
      "id" : 0,
      "type" : "KEY",
      "size" : 1,
      "text" : "+",
      "codeOptions" : [ "43", "123", "166", null ],
      "displayOptions" : [ [ "", "", "", "" ], [ "", "", "", "" ], [ "", "", "", "" ] ]
    }, {
      "id" : 0,
      "type" : "KEY",
      "size" : 1,
      "text" : "-",
      "codeOptions" : [ "45", "180", "124", null ],
      "displayOptions" : [ [ "", "", "", "" ], [ "", "", "", "" ], [ "", "", "", "" ] ]
    }, {
      "id" : 0,
      "type" : "KEY",
      "size" : 1,
      "text" : "",
      "codeOptions" : [ "92", "168", "169", null ],
      "displayOptions" : [ [ "", "", "", "" ], [ "", "", "", "" ], [ "", "", "", "" ] ]
    }, {
      "id" : 0,
      "type" : "FILLER",
      "size" : 2
    }, {
      "id" : 0,
      "type" : "FUNCTION",
      "name" : "INSERT",
      "size" : 2,
      "symbol" : true,
      "text" : "",
      "codeOptions" : [ "148", "148", "148", null ]
    }, {
      "id" : 0,
      "type" : "FUNCTION",
      "name" : "DELETE",
      "symbol" : true,
      "size" : 2,
      "text" : "",
      "codeOptions" : [ "20", "20", "20", null ]
    }, {
      "id" : 0,
      "type" : "FILLER",
      "size" : 0.3
    }, {
      "id" : 0,
      "type" : "FUNCTION",
      "name" : "DIR",
      "size" : 3,
      "text" : "DIR"
    } ]
  }, {
    "keys" : [ {
      "id" : 0,
      "type" : "FILLER",
      "size" : 0.3
    }, {
      "id" : 0,
      "type" : "OPTION",
      "index" : 16,
      "toggleButton" : true,
      "size" : 1.5,
      "text" : "CT",
      "codeOptions" : [ null, null, null, null ]
    }, {
      "id" : 0,
      "type" : "KEY",
      "size" : 1,
      "text" : "Q",
      "codeOptions" : [ "81", "113", "171", null ],
      "displayOptions" : [ [ "", "", "", "" ], [ "", "", "", "" ], [ "", "", "", "" ] ]
    }, {
      "id" : 0,
      "type" : "KEY",
      "size" : 1,
      "text" : "W",
      "codeOptions" : [ "87", "215", "179", null ],
      "displayOptions" : [ [ "", "", "", "" ], [ "", "", "", "" ], [ "", "", "", "" ] ]
    }, {
      "id" : 0,
      "type" : "KEY",
      "size" : 1,
      "text" : "E",
      "codeOptions" : [ "69", "197", "177", null ],
      "displayOptions" : [ [ "", "", "", "" ], [ "", "", "", "" ], [ "", "", "", "" ] ]
    }, {
      "id" : 0,
      "type" : "KEY",
      "size" : 1,
      "text" : "R",
      "codeOptions" : [ "82", "210", "178", null ],
      "displayOptions" : [ [ "", "", "", "" ], [ "", "", "", "" ], [ "", "", "", "" ] ]
    }, {
      "id" : 0,
      "type" : "KEY",
      "size" : 1,
      "text" : "T",
      "codeOptions" : [ "84", "212", "163", null ],
      "displayOptions" : [ [ "", "", "", "" ], [ "", "", "", "" ], [ "", "", "", "" ] ]
    }, {
      "id" : 0,
      "type" : "KEY",
      "size" : 1,
      "text" : "Y",
      "codeOptions" : [ "89", "217", "183", null ],
      "displayOptions" : [ [ "", "", "", "" ], [ "", "", "", "" ], [ "", "", "", "" ] ]
    }, {
      "id" : 0,
      "type" : "KEY",
      "size" : 1,
      "text" : "U",
      "codeOptions" : [ "85", "213", "184", null ],
      "displayOptions" : [ [ "", "", "", "" ], [ "", "", "", "" ], [ "", "", "", "" ] ]
    }, {
      "id" : 0,
      "type" : "KEY",
      "size" : 1,
      "text" : "I",
      "codeOptions" : [ "73", "201", "162", null ],
      "displayOptions" : [ [ "", "", "", "" ], [ "", "", "", "" ], [ "", "", "", "" ] ]
    }, {
      "id" : 0,
      "type" : "KEY",
      "size" : 1,
      "text" : "O",
      "codeOptions" : [ "79", "207", "185", null ],
      "displayOptions" : [ [ "", "", "", "" ], [ "", "", "", "" ], [ "", "", "", "" ] ]
    }, {
      "id" : 0,
      "type" : "KEY",
      "size" : 1,
      "text" : "P",
      "codeOptions" : [ "80", "208", "175", null ],
      "displayOptions" : [ [ "", "", "", "" ], [ "", "", "", "" ], [ "", "", "", "" ] ]
    }, {
      "id" : 0,
      "type" : "KEY",
      "size" : 1,
      "text" : "@",
      "codeOptions" : [ "64", "186", "164", null ],
      "displayOptions" : [ [ "", "", "", "" ], [ "", "", "", "" ], [ "", "", "", "" ] ]
    }, {
      "id" : 0,
      "type" : "KEY",
      "size" : 1,
      "text" : "*",
      "codeOptions" : [ "42", "192", "223", null ],
      "displayOptions" : [ [ "", "", "", "" ], [ "", "", "", "" ], [ "", "", "", "" ] ]
    }, {
      "id" : 0,
      "type" : "KEY",
      "size" : 1,
      "text" : "",
      "codeOptions" : [ "94", "222", "222", null ],
      "displayOptions" : [ [ "", "", "", "" ], [ "", "", "", "" ], [ "", "", "", "" ] ]
    }, {
      "id" : 0,
      "type" : "FILLER",
      "size" : 5.8
    }, {
      "id" : 0,
      "type" : "FUNCTION",
      "name" : "LOAD *",
      "size" : 4,
      "text" : "LOAD *"
    } ]
  }, {
    "keys" : [ {
      "id" : 0,
      "type" : "FILLER",
      "size" : 2
    }, {
      "id" : 0,
      "type" : "KEY",
      "size" : 1,
      "text" : "A",
      "codeOptions" : [ "65", "193", "176", null ],
      "displayOptions" : [ [ "", "", "", "" ], [ "", "", "", "" ], [ "", "", "", "" ] ]
    }, {
      "id" : 0,
      "type" : "KEY",
      "size" : 1,
      "text" : "S",
      "codeOptions" : [ "83", "211", "174", null ],
      "displayOptions" : [ [ "", "", "", "" ], [ "", "", "", "" ], [ "", "", "", "" ] ]
    }, {
      "id" : 0,
      "type" : "KEY",
      "size" : 1,
      "text" : "D",
      "codeOptions" : [ "68", "196", "172", null ],
      "displayOptions" : [ [ "", "", "", "" ], [ "", "", "", "" ], [ "", "", "", "" ] ]
    }, {
      "id" : 0,
      "type" : "KEY",
      "size" : 1,
      "text" : "F",
      "codeOptions" : [ "70", "198", "187", null ],
      "displayOptions" : [ [ "", "", "", "" ], [ "", "", "", "" ], [ "", "", "", "" ] ]
    }, {
      "id" : 0,
      "type" : "KEY",
      "size" : 1,
      "text" : "G",
      "codeOptions" : [ "71", "199", "165", null ],
      "displayOptions" : [ [ "", "", "", "" ], [ "", "", "", "" ], [ "", "", "", "" ] ]
    }, {
      "id" : 0,
      "type" : "KEY",
      "size" : 1,
      "text" : "H",
      "codeOptions" : [ "72", "200", "180", null ],
      "displayOptions" : [ [ "", "", "", "" ], [ "", "", "", "" ], [ "", "", "", "" ] ]
    }, {
      "id" : 0,
      "type" : "KEY",
      "size" : 1,
      "text" : "J",
      "codeOptions" : [ "74", "202", "181", null ],
      "displayOptions" : [ [ "", "", "", "" ], [ "", "", "", "" ], [ "", "", "", "" ] ]
    }, {
      "id" : 0,
      "type" : "KEY",
      "size" : 1,
      "text" : "K",
      "codeOptions" : [ "75", "203", "161", null ],
      "displayOptions" : [ [ "", "", "", "" ], [ "", "", "", "" ], [ "", "", "", "" ] ]
    }, {
      "id" : 0,
      "type" : "KEY",
      "size" : 1,
      "text" : "L",
      "codeOptions" : [ "76", "204", "182", null ],
      "displayOptions" : [ [ "", "", "", "" ], [ "", "", "", "" ], [ "", "", "", "" ] ]
    }, {
      "id" : 0,
      "type" : "KEY",
      "size" : 1,
      "text" : ":",
      "codeOptions" : [ "58", "91", "91", null ],
      "displayOptions" : [ [ "", "", "", "" ], [ "", "", "", "" ], [ "", "", "", "" ] ]
    }, {
      "id" : 0,
      "type" : "KEY",
      "size" : 1,
      "text" : ";",
      "codeOptions" : [ "59", "93", "93", null ],
      "displayOptions" : [ [ "", "", "", "" ], [ "", "", "", "" ], [ "", "", "", "" ] ]
    }, {
      "id" : 0,
      "type" : "KEY",
      "size" : 1,
      "text" : "=",
      "codeOptions" : [ "61", "61", "61", null ],
      "displayOptions" : [ [ "", "", "", "" ], [ "", "", "", "" ], [ "", "", "", "" ] ]
    }, {
      "id" : 0,
      "type" : "KEY",
      "symbol" : true,
      "name" : "RETURN",
      "size" : 2.3,
      "text" : "",
      "codeOptions" : [ "13", "141", "141", null ],
      "displayOptions" : [ [ "", "", "", "" ], [ "", "", "", "" ], [ "", "", "", "" ] ]
    }, {
      "id" : 0,
      "type" : "OPTION",
      "toggleButton" : true,
      "name" : "FRAME_COLOR",
      "size" : 2,
      "index" : 32,
      "text" : "FC"
    }, {
      "id" : 0,
      "type" : "OPTION",
      "toggleButton" : true,
      "name" : "FRAME_COLOR",
      "size" : 2,
      "index" : 64,
      "text" : "BC"
    } ]
  }, {
    "keys" : [ {
      "id" : 0,
      "type" : "OPTION",
      "symbol" : true,
      "name" : "COMMODORE",
      "index" : 2,
      "toggleButton" : true,
      "size" : 1,
      "text" : "",
      "codeOptions" : [ null, null, null, null ]
    }, {
      "id" : 0,
      "type" : "OPTION",
      "index" : 1,
      "symbol" : true,
      "name" : "SHIFT",
      "toggleButton" : true,
      "size" : 1.5,
      "text" : "",
      "codeOptions" : [ null, null, null, null ]
    }, {
      "id" : 0,
      "type" : "KEY",
      "size" : 1,
      "text" : "Z",
      "codeOptions" : [ "90", "218", "173", null ],
      "displayOptions" : [ [ "", "", "", "" ], [ "", "", "", "" ], [ "", "", "", "" ] ]
    }, {
      "id" : 0,
      "type" : "KEY",
      "size" : 1,
      "text" : "X",
      "codeOptions" : [ "88", "216", "189", null ],
      "displayOptions" : [ [ "", "", "", "" ], [ "", "", "", "" ], [ "", "", "", "" ] ]
    }, {
      "id" : 0,
      "type" : "KEY",
      "size" : 1,
      "text" : "C",
      "codeOptions" : [ "67", "195", "188", null ],
      "displayOptions" : [ [ "", "", "", "" ], [ "", "", "", "" ], [ "", "", "", "" ] ]
    }, {
      "id" : 0,
      "type" : "KEY",
      "size" : 1,
      "text" : "V",
      "codeOptions" : [ "86", "214", "190", null ],
      "displayOptions" : [ [ "", "", "", "" ], [ "", "", "", "" ], [ "", "", "", "" ] ]
    }, {
      "id" : 0,
      "type" : "KEY",
      "size" : 1,
      "text" : "B",
      "codeOptions" : [ "66", "194", "191", null ],
      "displayOptions" : [ [ "", "", "", "" ], [ "", "", "", "" ], [ "", "", "", "" ] ]
    }, {
      "id" : 0,
      "type" : "KEY",
      "size" : 1,
      "text" : "N",
      "codeOptions" : [ "78", "206", "170", null ],
      "displayOptions" : [ [ "", "", "", "" ], [ "", "", "", "" ], [ "", "", "", "" ] ]
    }, {
      "id" : 0,
      "type" : "KEY",
      "size" : 1,
      "text" : "M",
      "codeOptions" : [ "77", "205", "167", null ],
      "displayOptions" : [ [ "", "", "", "" ], [ "", "", "", "" ], [ "", "", "", "" ] ]
    }, {
      "id" : 0,
      "type" : "KEY",
      "size" : 1,
      "text" : ",",
      "codeOptions" : [ "44", "60", "60", null ],
      "displayOptions" : [ [ "", "", "", "" ], [ "", "", "", "" ], [ "", "", "", "" ] ]
    }, {
      "id" : 0,
      "type" : "KEY",
      "size" : 1,
      "text" : ".",
      "codeOptions" : [ "46", "62", "62", null ],
      "displayOptions" : [ [ "", "", "", "" ], [ "", "", "", "" ], [ "", "", "", "" ] ]
    }, {
      "id" : 0,
      "type" : "KEY",
      "size" : 1,
      "text" : "/",
      "codeOptions" : [ "47", "63", "63", null ],
      "displayOptions" : [ [ "", "", "", "" ], [ "", "", "", "" ], [ "", "", "", "" ] ]
    }, {
      "id" : 0,
      "type" : "FILLER",
      "size" : 1.75
    }, {
      "id" : 0,
      "type" : "FUNCTION",
      "name" : "UP",
      "symbol" : true,
      "size" : 1,
      "text" : "",
      "codeOptions" : [ "145", "145", "145", null ]
    } ]
  }, {
    "keys" : [ {
      "id" : 0,
      "type" : "FILLER",
      "size" : 2.66
    }, {
      "id" : 0,
      "type" : "KEY",
      "size" : 9,
      "text" : "SPACE",
      "codeOptions" : [ "32", "160", "160", null ]
    }, {
      "id" : 0,
      "type" : "FILLER",
      "size" : 1.6
    }, {
      "id" : 0,
      "type" : "FUNCTION",
      "name" : "LEFT",
      "symbol" : true,
      "size" : 1,
      "text" : "",
      "codeOptions" : [ "157", "157", "157", null ]
    }, {
      "id" : 0,
      "type" : "FUNCTION",
      "name" : "DOWN",
      "symbol" : true,
      "size" : 1,
      "text" : "",
      "codeOptions" : [ "17", "17", "17", null ]
    }, {
      "id" : 0,
      "type" : "FUNCTION",
      "name" : "RIGHT",
      "symbol" : true,
      "size" : 1,
      "text" : "",
      "codeOptions" : [ "29", "29", "29", null ]
    }, {
      "id" : 0,
      "type" : "KEY",
      "symbol" : true,
      "size" : 4,
      "name" : "RUN/STOP",
      "text" : "",
      "codeOptions" : [ "3", "131", "131 ", null ],
      "displayOptions" : [ [ "", "", "", "" ], [ "", "", "", "" ], [ "", "", "", "" ] ]
    } ]
  } ]
}